4bit-Processor/src/control_unit.vhd
library IEEE;
use IEEE.STD_LOGIC_1164.ALL;
use IEEE.NUMERIC_STD.ALL;

entity control_unit is
    Port (
        clk         : in  STD_LOGIC;
        reset       : in  STD_LOGIC;
        opcode      : in  STD_LOGIC_VECTOR(3 downto 0);
        zero_flag   : in  STD_LOGIC;

        pc_enable   : out STD_LOGIC;
        reg_write   : out STD_LOGIC;
        halt        : out STD_LOGIC;
        alu_op      : out STD_LOGIC_VECTOR(3 downto 0)
    );
end control_unit;

architecture Behavioral of control_unit is

    type state_type is (FETCH, DECODE, EXECUTE);
    signal state : state_type := FETCH;

begin
    process(clk, reset)
    begin
        if reset = '1' then
            state <= FETCH;

        elsif rising_edge(clk) then
            case state is
                when FETCH =>
                    state <= DECODE;

                when DECODE =>
                    state <= EXECUTE;

                when EXECUTE =>
                    state <= FETCH;
            end case;
        end if;
    end process;

    process(state, opcode)
    begin

        -- Default outputs
        pc_enable <= '0';
        reg_write <= '0';
        halt      <= '0';
        alu_op    <= "0000";

        case state is
            when FETCH =>
                pc_enable <= '1';

            when DECODE =>
                null;

            when EXECUTE =>
                case opcode is
                    when "0011" =>     -- ADD
                        alu_op <= "0000";
                        reg_write <= '1';

                    when "0100" =>     -- SUB
                        alu_op <= "0001";
                        reg_write <= '1';

                    when "0101" =>     -- AND
                        alu_op <= "0010";
                        reg_write <= '1';

                    when "0110" =>     -- OR
                        alu_op <= "0011";
                        reg_write <= '1';

                    when "0111" =>     -- XOR
                        alu_op <= "0100";
                        reg_write <= '1';

                    when "1000" =>     -- NOT
                        alu_op <= "0101";
                        reg_write <= '1';

                    when "1011" =>     -- HLT
                        halt <= '1';

                    when others =>
                        null;
                end case;
        end case;
    end process;
end Behavioral;

4bit-Processor/src/alu.vhd
library IEEE;
use IEEE.STD_LOGIC_1164.ALL;
use IEEE.NUMERIC_STD.ALL;

entity alu is
    Port (
        A       : in  STD_LOGIC_VECTOR(3 downto 0);
        B       : in  STD_LOGIC_VECTOR(3 downto 0);
        ALU_OP  : in  STD_LOGIC_VECTOR(3 downto 0);

        RESULT  : out STD_LOGIC_VECTOR(3 downto 0);
        ZERO    : out STD_LOGIC
    );
end alu;

architecture Behavioral of alu is
    signal result_int : STD_LOGIC_VECTOR(3 downto 0);
begin
    process(A, B, ALU_OP)
    begin
        case ALU_OP is
            when "0000" =>
                result_int <= std_logic_vector(unsigned(A) + unsigned(B));

            when "0001" =>
                result_int <= std_logic_vector(unsigned(A) - unsigned(B));

            when "0010" =>
                result_int <= A and B;

            when "0011" =>
                result_int <= A or B;

            when "0100" =>
                result_int <= A xor B;

            when "0101" =>
                result_int <= not A;

            when others =>
                result_int <= (others => '0');

        end case;

    end process;

    RESULT <= result_int;

    ZERO <= '1' when result_int = "0000" else '0';

end Behavioral;

4bit-Processor/src/register_file.vhd
library IEEE;
use IEEE.STD_LOGIC_1164.ALL;
use IEEE.NUMERIC_STD.ALL;

entity register_file is
    Port (
        clk         : in  STD_LOGIC;
        we          : in  STD_LOGIC;

        read_addr1  : in  STD_LOGIC_VECTOR(1 downto 0);
        read_addr2  : in  STD_LOGIC_VECTOR(1 downto 0);
        write_addr  : in  STD_LOGIC_VECTOR(1 downto 0);

        write_data  : in  STD_LOGIC_VECTOR(3 downto 0);

        read_data1  : out STD_LOGIC_VECTOR(3 downto 0);
        read_data2  : out STD_LOGIC_VECTOR(3 downto 0)
    );
end register_file;

architecture Behavioral of register_file is
    type reg_array is array (0 to 3) of STD_LOGIC_VECTOR(3 downto 0);
    signal regs : reg_array := (others => (others => '0'));
begin
    process(clk)
    begin
        if rising_edge(clk) then
            if we = '1' then
                regs(to_integer(unsigned(write_addr))) <= write_data;
            end if;
        end if;
    end process;

    read_data1 <= regs(to_integer(unsigned(read_addr1)));
    read_data2 <= regs(to_integer(unsigned(read_addr2)));
end Behavioral;

4bit-Processor/src/instruction_memory.vhd
library IEEE;
use IEEE.STD_LOGIC_1164.ALL;
use IEEE.NUMERIC_STD.ALL;

entity instruction_memory is
    Port (
        address     : in  STD_LOGIC_VECTOR(3 downto 0);
        instruction : out STD_LOGIC_VECTOR(7 downto 0)
    );
end instruction_memory;

architecture Behavioral of instruction_memory is

    type rom_type is array (0 to 15) of STD_LOGIC_VECTOR(7 downto 0);

    constant ROM : rom_type := (

        0 => "00010011", -- LDI R0,3
        1 => "00010110", -- LDI R1,2
        2 => "00100001", -- ADD
        3 => "00110001", -- SUB
        4 => "01100001", -- XOR
        5 => "10110000", -- HLT

        others => "00000000"
    );

begin

    instruction <= ROM(to_integer(unsigned(address)));

end Behavioral;

4bit-Processor/src/program_counter.vhd
library IEEE;
use IEEE.STD_LOGIC_1164.ALL;
use IEEE.NUMERIC_STD.ALL;

entity program_counter is
    Port (
        clk     : in  STD_LOGIC;
        reset   : in  STD_LOGIC;
        enable  : in  STD_LOGIC;
        load    : in  STD_LOGIC;
        pc_in   : in  STD_LOGIC_VECTOR(3 downto 0);

        pc_out  : out STD_LOGIC_VECTOR(3 downto 0)
    );
end program_counter;

architecture Behavioral of program_counter is
    signal pc_reg : unsigned(3 downto 0) := (others => '0');
begin
    process(clk, reset)
    begin
        if reset = '1' then
            pc_reg <= (others => '0');

        elsif rising_edge(clk) then
            if load = '1' then
                pc_reg <= unsigned(pc_in);

            elsif enable = '1' then
                pc_reg <= pc_reg + 1;
            end if;
        end if;
    end process;

    pc_out <= std_logic_vector(pc_reg);
end Behavioral;

4bit-Processor/src/cpu_top.vhd
library IEEE;
use IEEE.STD_LOGIC_1164.ALL;
use IEEE.NUMERIC_STD.ALL;

entity cpu_top is
    Port (
        clk   : in  STD_LOGIC;
        reset : in  STD_LOGIC
    );
end cpu_top;

architecture Structural of cpu_top is
    -- Program Counter
    signal pc             : STD_LOGIC_VECTOR(3 downto 0);
    signal pc_enable      : STD_LOGIC;
    signal pc_load        : STD_LOGIC := '0';

    -- Instruction
    signal instruction    : STD_LOGIC_VECTOR(7 downto 0);
    signal opcode         : STD_LOGIC_VECTOR(3 downto 0);

    -- Register File
    signal reg_write      : STD_LOGIC;
    signal read_data1     : STD_LOGIC_VECTOR(3 downto 0);
    signal read_data2     : STD_LOGIC_VECTOR(3 downto 0);
    signal alu_result     : STD_LOGIC_VECTOR(3 downto 0);

    -- ALU
    signal alu_op         : STD_LOGIC_VECTOR(3 downto 0);
    signal zero_flag      : STD_LOGIC;

    -- Halt
    signal halt           : STD_LOGIC;
begin

-- Program Counter
PC_INST : entity work.program_counter
port map(
    clk     => clk,
    reset   => reset,
    enable  => pc_enable,
    load    => pc_load,
    pc_in   => (others => '0'),
    pc_out  => pc
);

-- Instruction Memory
ROM_INST : entity work.instruction_memory
port map(
    address     => pc,
    instruction => instruction
);

opcode <= instruction(7 downto 4);

-- Register File
REG_INST : entity work.register_file
port map(
    clk         => clk,
    we          => reg_write,

    read_addr1  => "00",
    read_addr2  => "01",
    write_addr  => "00",

    write_data  => alu_result,

    read_data1  => read_data1,
    read_data2  => read_data2
);

-- ALU
ALU_INST : entity work.alu
port map(
    A       => read_data1,
    B       => read_data2,

    ALU_OP  => alu_op,

    RESULT  => alu_result,
    ZERO    => zero_flag
);

-- Control Unit
CTRL_INST : entity work.control_unit
port map(

    clk         => clk,
    reset       => reset,

    opcode      => opcode,
    zero_flag   => zero_flag,

    pc_enable   => pc_enable,
    reg_write   => reg_write,
    halt        => halt,
    alu_op      => alu_op
);
end Structural;

4bit-Processor/tb/cpu_tb.vhd
library IEEE;
use IEEE.STD_LOGIC_1164.ALL;

entity cpu_tb is
end cpu_tb;

architecture Behavioral of cpu_tb is
    signal clk   : STD_LOGIC := '0';
    signal reset : STD_LOGIC := '1';
begin
    DUT : entity work.cpu_top
    port map(
        clk   => clk,
        reset => reset
    );

    clk_process : process
    begin
        while true loop
            clk <= '0';
            wait for 10 ns;

            clk <= '1';
            wait for 10 ns;
        end loop;
    end process;

    stimulus : process
    begin
        wait for 20 ns;

        reset <= '0';

        wait for 500 ns;

        wait;
    end process;
end Behavioral;

4bit-Processor/waveforms/cpu.vcd
$date
  Mon Jun 22 12:30:33 2026
$end
$version
  GHDL v0
$end
$timescale
  1 fs
$end
$scope module standard $end
$upscope $end
$scope module std_logic_1164 $end
$upscope $end
$scope module numeric_std $end
$upscope $end
$scope module cpu_tb $end
$var reg 1 ! clk $end
$var reg 1 " reset $end
$scope module dut $end
$var reg 1 # clk $end
$var reg 1 $ reset $end
$var reg 4 % pc[3:0] $end
$var reg 1 & pc_enable $end
$var reg 1 ' pc_load $end
$var reg 8 ( instruction[7:0] $end
$var reg 4 ) opcode[3:0] $end
$var reg 1 * reg_write $end
$var reg 4 + read_data1[3:0] $end
$var reg 4 , read_data2[3:0] $end
$var reg 4 - alu_result[3:0] $end
$var reg 4 . alu_op[3:0] $end
$var reg 1 / zero_flag $end
$var reg 1 0 halt $end
$scope module pc_inst $end
$var reg 1 1 clk $end
$var reg 1 2 reset $end
$var reg 1 3 enable $end
$var reg 1 4 load $end
$var reg 4 5 pc_in[3:0] $end
$var reg 4 6 pc_out[3:0] $end
$var reg 4 7 pc_reg[3:0] $end
$upscope $end
$scope module rom_inst $end
$var reg 4 8 address[3:0] $end
$var reg 8 9 instruction[7:0] $end
$upscope $end
$scope module reg_inst $end
$var reg 1 : clk $end
$var reg 1 ; we $end
$var reg 2 < read_addr1[1:0] $end
$var reg 2 = read_addr2[1:0] $end
$var reg 2 > write_addr[1:0] $end
$var reg 4 ? write_data[3:0] $end
$var reg 4 @ read_data1[3:0] $end
$var reg 4 A read_data2[3:0] $end
$comment regs is not handled $end
$upscope $end
$scope module alu_inst $end
$var reg 4 B a[3:0] $end
$var reg 4 C b[3:0] $end
$var reg 4 D alu_op[3:0] $end
$var reg 4 E result[3:0] $end
$var reg 1 F zero $end
$var reg 4 G result_int[3:0] $end
$upscope $end
$scope module ctrl_inst $end
$var reg 1 H clk $end
$var reg 1 I reset $end
$var reg 4 J opcode[3:0] $end
$var reg 1 K zero_flag $end
$var reg 1 L pc_enable $end
$var reg 1 M reg_write $end
$var reg 1 N halt $end
$var reg 4 O alu_op[3:0] $end
$comment state is not handled $end
$upscope $end
$upscope $end
$upscope $end
$enddefinitions $end
#0
0!
1"
0#
1$
b0000 %
1&
0'
b00010011 (
b0001 )
0*
b0000 +
b0000 ,
b0000 -
b0000 .
1/
00
01
12
13
04
b0000 5
b0000 6
b0000 7
b0000 8
b00010011 9
0:
0;
b00 <
b01 =
b00 >
b0000 ?
b0000 @
b0000 A
b0000 B
b0000 C
b0000 D
b0000 E
1F
b0000 G
0H
1I
b0001 J
1K
1L
0M
0N
b0000 O
#10000000
1!
1#
11
1:
1H
#20000000
0!
0"
0#
0$
01
02
0:
0H
0I
#30000000
1!
1#
b0001 %
0&
b00010110 (
11
03
b0001 6
b0001 7
b0001 8
b00010110 9
1:
1H
0L
#40000000
0!
0#
01
0:
0H
#50000000
1!
1#
11
1:
1H
#60000000
0!
0#
01
0:
0H
#70000000
1!
1#
1&
11
13
1:
1H
1L
#80000000
0!
0#
01
0:
0H
#90000000
1!
1#
b0010 %
0&
b00100001 (
b0010 )
11
03
b0010 6
b0010 7
b0010 8
b00100001 9
1:
1H
b0010 J
0L
#100000000
0!
0#
01
0:
0H
#110000000
1!
1#
11
1:
1H
#120000000
0!
0#
01
0:
0H
#130000000
1!
1#
1&
11
13
1:
1H
1L
#140000000
0!
0#
01
0:
0H
#150000000
1!
1#
b0011 %
0&
b00110001 (
b0011 )
11
03
b0011 6
b0011 7
b0011 8
b00110001 9
1:
1H
b0011 J
0L
#160000000
0!
0#
01
0:
0H
#170000000
1!
1#
1*
11
1:
1;
1H
1M
#180000000
0!
0#
01
0:
0H
#190000000
1!
1#
1&
0*
11
13
1:
0;
1H
1L
0M
#200000000
0!
0#
01
0:
0H
#210000000
1!
1#
b0100 %
0&
b01100001 (
b0110 )
11
03
b0100 6
b0100 7
b0100 8
b01100001 9
1:
1H
b0110 J
0L
#220000000
0!
0#
01
0:
0H
#230000000
1!
1#
1*
b0011 .
11
1:
1;
b0011 D
1H
1M
b0011 O
#240000000
0!
0#
01
0:
0H
#250000000
1!
1#
1&
0*
b0000 .
11
13
1:
0;
b0000 D
1H
1L
0M
b0000 O
#260000000
0!
0#
01
0:
0H
#270000000
1!
1#
b0101 %
0&
b10110000 (
b1011 )
11
03
b0101 6
b0101 7
b0101 8
b10110000 9
1:
1H
b1011 J
0L
#280000000
0!
0#
01
0:
0H
#290000000
1!
1#
10
11
1:
1H
1N
#300000000
0!
0#
01
0:
0H
#310000000
1!
1#
1&
00
11
13
1:
1H
1L
0N
#320000000
0!
0#
01
0:
0H
#330000000
1!
1#
b0110 %
0&
b00000000 (
b0000 )
11
03
b0110 6
b0110 7
b0110 8
b00000000 9
1:
1H
b0000 J
0L
#340000000
0!
0#
01
0:
0H
#350000000
1!
1#
11
1:
1H
#360000000
0!
0#
01
0:
0H
#370000000
1!
1#
1&
11
13
1:
1H
1L
#380000000
0!
0#
01
0:
0H
#390000000
1!
1#
b0111 %
0&
11
03
b0111 6
b0111 7
b0111 8
1:
1H
0L
#400000000
0!
0#
01
0:
0H
#410000000
1!
1#
11
1:
1H
#420000000
0!
0#
01
0:
0H
#430000000
1!
1#
1&
11
13
1:
1H
1L
#440000000
0!
0#
01
0:
0H
#450000000
1!
1#
b1000 %
0&
11
03
b1000 6
b1000 7
b1000 8
1:
1H
0L
#460000000
0!
0#
01
0:
0H
#470000000
1!
1#
11
1:
1H
#480000000
0!
0#
01
0:
0H
#490000000
1!
1#
1&
11
13
1:
1H
1L
