UART-VHDL/src/uart_tx.vhd
library ieee;
use ieee.std_logic_1164.all;
use ieee.numeric_std.all;

entity uart_tx is
    port (
        clk : in  std_logic;
        reset : in  std_logic;
        tick : in  std_logic;
        start : in  std_logic;
        data_in : in  std_logic_vector(7 downto 0);
        
        tx : out std_logic;
        busy : out std_logic
    );
end entity uart_tx;

architecture Behavioral of uart_tx is
    type state_type is (
        IDLE,
        START_BIT,
        DATA_BITS,
        STOP_BIT
    );

    signal current_state : state_type := IDLE;
    signal shift_reg : std_logic_vector(7 downto 0);
    signal bit_index : integer range 0 to 7 := 0;

begin
    process(clk, reset)
    begin
        if reset = '1' then
            current_state <= IDLE;
            shift_reg <= (others => '0');
            bit_index <= 0;
            tx <= '1';
            busy <= '0';

        elsif rising_edge(clk) then
            case current_state is
                when IDLE =>
                    tx <= '1';
                    busy <= '0';
                    if start = '1' then
                        shift_reg <= data_in;
                        bit_index <= 0;
                        busy <= '1';
                        current_state <= START_BIT;
                    end if;
                when START_BIT =>
                    tx <= '0';
                    busy <= '1';
                    if tick = '1' then
                        current_state <= DATA_BITS;
                    end if;
                when DATA_BITS =>
                    busy <= '1';
                    tx <= shift_reg(bit_index);
                    if tick = '1' then
                        if bit_index = 7 then
                            current_state <= STOP_BIT;
                            bit_index <= 0;
                        else
                            bit_index <= bit_index + 1;
                            current_state <= DATA_BITS;
                        end if;
                    end if;
                when STOP_BIT =>
                    tx <= '1';
                    busy <= '1';
                    if tick = '1' then
                        current_state <= IDLE;
                    end if;
                when others =>
                    current_state <= IDLE;
            end case;
        end if;
    end process;
end Behavioral;

UART-VHDL/tb/uart_tb.vhd
library ieee;
use ieee.std_logic_1164.all;
use ieee.numeric_std.all;

entity uart_tb is
end uart_tb;

architecture Behavioral of uart_tb is
    
    signal clk : std_logic := '0';
    signal reset : std_logic := '0';
    signal tick : std_logic := '0';
    signal start : std_logic := '0';

    signal data_in : std_logic_vector(7 downto 0);

    signal tx : std_logic;
    signal busy : std_logic;

    begin
        -- uut : unit under test
        uut : entity work.uart_tx
            port map (
                clk => clk,
                reset => reset,
                tick => tick,
                start => start,
                data_in => data_in,
                tx => tx,
                busy => busy
            );

        -- Clock generation : for 50 MHz clock (20 ns period)
        clock_process : process
        begin
            while true loop
                clk <= '0';
                wait for 10 ns;
                clk <= '1';
                wait for 10 ns;
            end loop;
        end process;

        tick_process : process
        begin
            while true loop
                tick <= '0';
                wait for 180 ns;
                
                tick <= '1';
                wait for 20 ns;
            end loop;
        end process;

        stimulus_process : process
        begin
            -- Reset the system
            reset <= '1';
            wait for 100 ns;
            reset <= '0';
            wait for 100 ns;
            -- Send a byte of data
            data_in <= "01000001"; -- ASCII 'A'
            start <= '1';
            wait for 20 ns;
            start <= '0';

            wait until busy = '0'; -- Wait until transmission is complete
            wait for 100 ns; -- Wait before ending simulation
            assert false 
            report "End of simulation" 
            severity failure;
        end process;
end Behavioral;

UART-VHDL/waveforms/uart.vcd
$date
  Mon Jun 22 06:37:36 2026
$end
$version
  GHDL v0
$end
$timescale
  1 fs
$end
$scope module standard $end
$upscope $end
$scope module std_logic_1164 $end
$upscope $end
$scope module numeric_std $end
$upscope $end
$scope module uart_tb $end
$var reg 1 ! clk $end
$var reg 1 " reset $end
$var reg 1 # tick $end
$var reg 1 $ start $end
$var reg 8 % data_in[7:0] $end
$var reg 1 & tx $end
$var reg 1 ' busy $end
$scope module uut $end
$var reg 1 ( clk $end
$var reg 1 ) reset $end
$var reg 1 * tick $end
$var reg 1 + start $end
$var reg 8 , data_in[7:0] $end
$var reg 1 - tx $end
$var reg 1 . busy $end
$comment current_state is not handled $end
$var reg 8 / shift_reg[7:0] $end
$var integer 32 0 bit_index $end
$upscope $end
$upscope $end
$enddefinitions $end
#0
0!
1"
0#
0$
bUUUUUUUU %
1&
0'
0(
1)
0*
0+
bUUUUUUUU ,
1-
0.
b00000000 /
b0 0
#10000000
1!
1(
#20000000
0!
0(
#30000000
1!
1(
#40000000
0!
0(
#50000000
1!
1(
#60000000
0!
0(
#70000000
1!
1(
#80000000
0!
0(
#90000000
1!
1(
#100000000
0!
0"
0(
0)
#108000000
1#
1*
#110000000
1!
1(
#120000000
0!
0(
#128000000
0#
0*
#130000000
1!
1(
#140000000
0!
0(
#150000000
1!
1(
#160000000
0!
0(
#170000000
1!
1(
#180000000
0!
0(
#190000000
1!
1(
#200000000
0!
1$
b01000001 %
0(
1+
b01000001 ,
#210000000
1!
1'
1(
1.
b01000001 /
#220000000
0!
0$
0(
0+
#230000000
1!
0&
1(
0-
#236000000
1#
1*
#240000000
0!
0(
#250000000
1!
1&
1(
1-
b1 0
#256000000
0#
0*
#260000000
0!
0(
#270000000
1!
0&
1(
0-
#280000000
0!
0(
#290000000
1!
1(
#300000000
0!
0(
#310000000
1!
1(
#320000000
0!
0(
#330000000
1!
1(
#340000000
0!
0(
#350000000
1!
1(
#360000000
0!
0(
#364000000
1#
1*
#370000000
1!
1(
b10 0
#380000000
0!
0(
#384000000
0#
0*
#390000000
1!
1(
#400000000
0!
0(
#410000000
1!
1(
#420000000
0!
0(
#430000000
1!
1(
#440000000
0!
0(
#450000000
1!
1(
#460000000
0!
0(
#470000000
1!
1(
#480000000
0!
0(
#490000000
1!
1(
#492000000
1#
1*
#500000000
0!
0(
#510000000
1!
1(
b11 0
#512000000
0#
0*
#520000000
0!
0(
#530000000
1!
1(
#540000000
0!
0(
#550000000
1!
1(
#560000000
0!
0(
#570000000
1!
1(
#580000000
0!
0(
#590000000
1!
1(
#600000000
0!
0(
#610000000
1!
1(
#620000000
0!
1#
0(
1*
#630000000
1!
1(
b100 0
#640000000
0!
0#
0(
0*
#650000000
1!
1(
#660000000
0!
0(
#670000000
1!
1(
#680000000
0!
0(
#690000000
1!
1(
#700000000
0!
0(
#710000000
1!
1(
#720000000
0!
0(
#730000000
1!
1(
#740000000
0!
0(
#748000000
1#
1*
#750000000
1!
1(
b101 0
#760000000
0!
0(
#768000000
0#
0*
#770000000
1!
1(
#780000000
0!
0(
#790000000
1!
1(
#800000000
0!
0(
#810000000
1!
1(
#820000000
0!
0(
#830000000
1!
1(
#840000000
0!
0(
#850000000
1!
1(
#860000000
0!
0(
#870000000
1!
1(
#876000000
1#
1*
#880000000
0!
0(
#890000000
1!
1(
b110 0
#896000000
0#
0*
#900000000
0!
0(
#910000000
1!
1&
1(
1-
#920000000
0!
0(
#930000000
1!
1(
#940000000
0!
0(
#950000000
1!
1(
#960000000
0!
0(
#970000000
1!
1(
#980000000
0!
0(
#990000000
1!
1(
#1000000000
0!
0(
#1004000000
1#
1*
#1010000000
1!
1(
b111 0
#1020000000
0!
0(
#1024000000
0#
0*
#1030000000
1!
0&
1(
0-
#1040000000
0!
0(
#1050000000
1!
1(
#1060000000
0!
0(
#1070000000
1!
1(
#1080000000
0!
0(
#1090000000
1!
1(
#1100000000
0!
0(
#1110000000
1!
1(
#1120000000
0!
0(
#1130000000
1!
1(
#1132000000
1#
1*
#1140000000
0!
0(
#1150000000
1!
1(
b0 0
#1152000000
0#
0*
#1160000000
0!
0(
#1170000000
1!
1&
1(
1-
#1180000000
0!
0(
#1190000000
1!
1(
#1200000000
0!
0(
#1210000000
1!
1(
#1220000000
0!
0(
#1230000000
1!
1(
#1240000000
0!
0(
#1250000000
1!
1(
#1260000000
0!
1#
0(
1*
#1270000000
1!
1(
#1280000000
0!
0#
0(
0*
#1290000000
1!
0'
1(
0.
#1300000000
0!
0(
#1310000000
1!
1(
#1320000000
0!
0(
#1330000000
1!
1(
#1340000000
0!
0(
#1350000000
1!
1(
#1360000000
0!
0(
#1370000000
1!
1(
#1380000000
0!
0(
#1388000000
1#
1*
#1390000000
1!
1$
b00110101 %
1'
1(
1+
b00110101 ,
1.
b00110101 /
#1400000000
0!
0(
#1408000000
0#
0*
#1410000000
1!
0$
0&
1(
0+
0-
#1420000000
0!
0(
#1430000000
1!
1&
1(
1-
#1440000000
0!
0(
#1450000000
1!
1(
#1460000000
0!
0(
#1470000000
1!
1(
#1480000000
0!
0(
#1490000000
1!
1(
#1500000000
0!
0(
#1510000000
1!
1(
#1516000000
1#
1*
#1520000000
0!
0(
#1530000000
1!
1(
b1 0
#1536000000
0#
0*
#1540000000
0!
0(
#1550000000
1!
0&
1(
0-
#1560000000
0!
0(
#1570000000
1!
1(
#1580000000
0!
0(
#1590000000
1!
1(
#1600000000
0!
0(
#1610000000
1!
1(
#1620000000
0!
0(
#1630000000
1!
1(
#1640000000
0!
0(
#1644000000
1#
1*
#1650000000
1!
1(
b10 0
#1660000000
0!
0(
#1664000000
0#
0*
#1670000000
1!
1&
1(
1-
#1680000000
0!
0(
#1690000000
1!
1(
#1700000000
0!
0(
#1710000000
1!
1(
#1720000000
0!
0(
#1730000000
1!
1(
#1740000000
0!
0(
#1750000000
1!
1(
#1760000000
0!
0(
#1770000000
1!
1(
#1772000000
1#
1*
#1780000000
0!
0(
#1790000000
1!
1(
b11 0
#1792000000
0#
0*
#1800000000
0!
0(
#1810000000
1!
0&
1(
0-
#1820000000
0!
0(
#1830000000
1!
1(
#1840000000
0!
0(
#1850000000
1!
1(
#1860000000
0!
0(
#1870000000
1!
1(
#1880000000
0!
0(
#1890000000
1!
1(
#1900000000
0!
1#
0(
1*
#1910000000
1!
1(
b100 0
#1920000000
0!
0#
0(
0*
#1930000000
1!
1&
1(
1-
#1940000000
0!
0(
#1950000000
1!
1(
#1960000000
0!
0(
#1970000000
1!
1(
#1980000000
0!
0(
#1990000000
1!
1(
#2000000000
0!
0(
#2010000000
1!
1(
#2020000000
0!
0(
#2028000000
1#
1*
#2030000000
1!
1(
b101 0
#2040000000
0!
0(
#2048000000
0#
0*
#2050000000
1!
1(
#2060000000
0!
0(
#2070000000
1!
1(
#2080000000
0!
0(
#2090000000
1!
1(
#2100000000
0!
0(
#2110000000
1!
1(
#2120000000
0!
0(
#2130000000
1!
1(
#2140000000
0!
0(
#2150000000
1!
1(
#2156000000
1#
1*
#2160000000
0!
0(
#2170000000
1!
1(
b110 0
#2176000000
0#
0*
#2180000000
0!
0(
#2190000000
1!
0&
1(
0-
#2200000000
0!
0(
#2210000000
1!
1(
#2220000000
0!
0(
#2230000000
1!
1(
#2240000000
0!
0(
#2250000000
1!
1(
#2260000000
0!
0(
#2270000000
1!
1(
#2280000000
0!
0(
#2284000000
1#
1*
#2290000000
1!
1(
b111 0
#2300000000
0!
0(
#2304000000
0#
0*
#2310000000
1!
1(
#2320000000
0!
0(
#2330000000
1!
1(
#2340000000
0!
0(
#2350000000
1!
1(
#2360000000
0!
0(
#2370000000
1!
1(
#2380000000
0!
0(
#2390000000
1!
1(
#2400000000
0!
0(
#2410000000
1!
1(
#2412000000
1#
1*
#2420000000
0!
0(
#2430000000
1!
1(
b0 0
#2432000000
0#
0*
#2440000000
0!
0(
#2450000000
1!
1&
1(
1-
#2460000000
0!
0(
#2470000000
1!
1(
#2480000000
0!
0(
#2490000000
1!
1(
#2500000000
0!
0(
#2510000000
1!
1(
#2520000000
0!
0(
#2530000000
1!
1(
#2540000000
0!
1#
0(
1*
#2550000000
1!
1(
#2560000000
0!
0#
0(
0*
#2570000000
1!
0'
1(
0.
#2580000000
0!
0(
#2590000000
1!
1(
#2600000000
0!
0(
#2610000000
1!
1(
#2620000000
0!
0(
#2630000000
1!
1(
#2640000000
0!
0(
#2650000000
1!
1(
#2660000000
0!
0(
#2668000000
1#
1*
#2670000000
1!
1$
b11111111 %
1'
1(
1+
b11111111 ,
1.
b11111111 /
#2680000000
0!
0(
#2688000000
0#
0*
#2690000000
1!
0$
0&
1(
0+
0-
#2700000000
0!
0(
#2710000000
1!
1&
1(
1-
#2720000000
0!
0(
#2730000000
1!
1(
#2740000000
0!
0(
#2750000000
1!
1(
#2760000000
0!
0(
#2770000000
1!
1(
#2780000000
0!
0(
#2790000000
1!
1(
#2796000000
1#
1*
#2800000000
0!
0(
#2810000000
1!
1(
b1 0
#2816000000
0#
0*
#2820000000
0!
0(
#2830000000
1!
1(
#2840000000
0!
0(
#2850000000
1!
1(
#2860000000
0!
0(
#2870000000
1!
1(
#2880000000
0!
0(
#2890000000
1!
1(
#2900000000
0!
0(
#2910000000
1!
1(
#2920000000
0!
0(
#2924000000
1#
1*
#2930000000
1!
1(
b10 0
#2940000000
0!
0(
#2944000000
0#
0*
#2950000000
1!
1(
#2960000000
0!
0(
#2970000000
1!
1(
#2980000000
0!
0(
#2990000000
1!
1(
#3000000000
0!
0(
#3010000000
1!
1(
#3020000000
0!
0(
#3030000000
1!
1(
#3040000000
0!
0(
#3050000000
1!
1(
#3052000000
1#
1*
#3060000000
0!
0(
#3070000000
1!
1(
b11 0
#3072000000
0#
0*
#3080000000
0!
0(
#3090000000
1!
1(
#3100000000
0!
0(
#3110000000
1!
1(
#3120000000
0!
0(
#3130000000
1!
1(
#3140000000
0!
0(
#3150000000
1!
1(
#3160000000
0!
0(
#3170000000
1!
1(
#3180000000
0!
1#
0(
1*
#3190000000
1!
1(
b100 0
#3200000000
0!
0#
0(
0*
#3210000000
1!
1(
#3220000000
0!
0(
#3230000000
1!
1(
#3240000000
0!
0(
#3250000000
1!
1(
#3260000000
0!
0(
#3270000000
1!
1(
#3280000000
0!
0(
#3290000000
1!
1(
#3300000000
0!
0(
#3308000000
1#
1*
#3310000000
1!
1(
b101 0
#3320000000
0!
0(
#3328000000
0#
0*
#3330000000
1!
1(
#3340000000
0!
0(
#3350000000
1!
1(
#3360000000
0!
0(
#3370000000
1!
1(
#3380000000
0!
0(
#3390000000
1!
1(
#3400000000
0!
0(
#3410000000
1!
1(
#3420000000
0!
0(
#3430000000
1!
1(
#3436000000
1#
1*
#3440000000
0!
0(
#3450000000
1!
1(
b110 0
#3456000000
0#
0*
#3460000000
0!
0(
#3470000000
1!
1(
#3480000000
0!
0(
#3490000000
1!
1(
#3500000000
0!
0(
#3510000000
1!
1(
#3520000000
0!
0(
#3530000000
1!
1(
#3540000000
0!
0(
#3550000000
1!
1(
#3560000000
0!
0(
#3564000000
1#
1*
#3570000000
1!
1(
b111 0
#3580000000
0!
0(
#3584000000
0#
0*
#3590000000
1!
1(
#3600000000
0!
0(
#3610000000
1!
1(
#3620000000
0!
0(
#3630000000
1!
1(
#3640000000
0!
0(
#3650000000
1!
1(
#3660000000
0!
0(
#3670000000
1!
1(
#3680000000
0!
0(
#3690000000
1!
1(
#3692000000
1#
1*
#3700000000
0!
0(
#3710000000
1!
1(
b0 0
#3712000000
0#
0*
#3720000000
0!
0(
#3730000000
1!
1(
#3740000000
0!
0(
#3750000000
1!
1(
#3760000000
0!
0(
#3770000000
1!
1(
#3780000000
0!
0(
#3790000000
1!
1(
#3800000000
0!
0(
#3810000000
1!
1(
#3820000000
0!
1#
0(
1*
#3830000000
1!
1(
#3840000000
0!
0#
0(
0*
#3850000000
1!
0'
1(
0.
#3860000000
0!
0(
#3870000000
1!
1(
#3880000000
0!
0(
#3890000000
1!
1(
#3900000000
0!
0(
#3910000000
1!
1(
#3920000000
0!
0(
#3930000000
1!
1(
#3940000000
0!
0(
#3948000000
1#
1*
