UART-VHDL/src/uart_rx.vhd
library IEEE;
use IEEE.STD_LOGIC_1164.ALL;
use IEEE.NUMERIC_STD.ALL;

entity uart_rx is
    Port(
        clk            : in  STD_LOGIC;
        reset          : in  STD_LOGIC;
        tick           : in  STD_LOGIC;
        rx             : in  STD_LOGIC;

        data_out       : out STD_LOGIC_VECTOR(7 downto 0);
        data_valid     : out STD_LOGIC;
        framing_error  : out STD_LOGIC
    );
end uart_rx;

architecture Behavioral of uart_rx is

    type state_type is (
        IDLE,
        START_BIT,
        DATA_BITS,
        STOP_BIT
    );

    signal current_state : state_type := IDLE;
    signal shift_reg      : STD_LOGIC_VECTOR(7 downto 0) := (others => '0');
    signal bit_index      : integer range 0 to 7 := 0;

begin

    process(clk, reset)
    begin
        if reset = '1' then

            current_state <= IDLE;
            shift_reg <= (others => '0');
            bit_index <= 0;

            data_out <= (others => '0');
            data_valid <= '0';
            framing_error <= '0';

        elsif rising_edge(clk) then

            -- Default outputs
            data_valid <= '0';
            framing_error <= '0';

            case current_state is

                when IDLE =>

                    if rx = '0' then
                        bit_index <= 0;
                        current_state <= START_BIT;
                    end if;

                when START_BIT =>

                    if tick = '1' then
                        current_state <= DATA_BITS;
                    end if;

                when DATA_BITS =>

                    if tick = '1' then

                        shift_reg(bit_index) <= rx;

                        if bit_index = 7 then
                            current_state <= STOP_BIT;
                        else
                            bit_index <= bit_index + 1;
                        end if;

                    end if;

                when STOP_BIT =>

                    if tick = '1' then

                        if rx = '1' then
                            data_out <= shift_reg;
                            data_valid <= '1';
                        else
                            framing_error <= '1';
                        end if;

                        current_state <= IDLE;

                    end if;

                when others =>

                    current_state <= IDLE;

            end case;

        end if;

    end process;

end Behavioral;

UART-VHDL/src/uart_tx.vhd
library ieee;
use ieee.std_logic_1164.all;
use ieee.numeric_std.all;

entity uart_tx is
    port (
        clk : in  std_logic;
        reset : in  std_logic;
        tick : in  std_logic;
        start : in  std_logic;
        data_in : in  std_logic_vector(7 downto 0);
        
        tx : out std_logic;
        busy : out std_logic
    );
end entity uart_tx;

architecture Behavioral of uart_tx is
    type state_type is (
        IDLE,
        START_BIT,
        DATA_BITS,
        STOP_BIT
    );

    signal current_state : state_type := IDLE;
    signal shift_reg : std_logic_vector(7 downto 0);
    signal bit_index : integer range 0 to 7 := 0;

begin
    process(clk, reset)
    begin
        if reset = '1' then
            current_state <= IDLE;
            shift_reg <= (others => '0');
            bit_index <= 0;
            tx <= '1';
            busy <= '0';

        elsif rising_edge(clk) then
            case current_state is
                when IDLE =>
                    tx <= '1';
                    busy <= '0';
                    if start = '1' then
                        shift_reg <= data_in;
                        bit_index <= 0;
                        busy <= '1';
                        current_state <= START_BIT;
                    end if;
                when START_BIT =>
                    tx <= '0';
                    busy <= '1';
                    if tick = '1' then
                        current_state <= DATA_BITS;
                    end if;
                when DATA_BITS =>
                    busy <= '1';
                    tx <= shift_reg(bit_index);
                    if tick = '1' then
                        if bit_index = 7 then
                            current_state <= STOP_BIT;
                            bit_index <= 0;
                        else
                            bit_index <= bit_index + 1;
                            current_state <= DATA_BITS;
                        end if;
                    end if;
                when STOP_BIT =>
                    tx <= '1';
                    busy <= '1';
                    if tick = '1' then
                        current_state <= IDLE;
                    end if;
                when others =>
                    current_state <= IDLE;
            end case;
        end if;
    end process;
end Behavioral;

UART-VHDL/src/uart_top.vhd
library IEEE;
use IEEE.STD_LOGIC_1164.ALL;

entity uart_top is
    Port(

        clk : in STD_LOGIC;
        reset : in STD_LOGIC;
        tick : in STD_LOGIC;

        start : in STD_LOGIC;
        data_in : in STD_LOGIC_VECTOR(7 downto 0);

        data_out : out STD_LOGIC_VECTOR(7 downto 0);
        data_valid : out STD_LOGIC;

        busy : out STD_LOGIC;
        framing_error : out STD_LOGIC

    );
end uart_top;

architecture Behavioral of uart_top is

    signal tx_wire : STD_LOGIC;

begin
    -- UART Transmitter
    tx_inst : entity work.uart_tx
    port map(

        clk => clk,
        reset => reset,
        tick => tick,

        start => start,
        data_in => data_in,

        tx => tx_wire,
        busy => busy

    );

    -- UART Receiver
    rx_inst : entity work.uart_rx
    port map(

        clk => clk,
        reset => reset,
        tick => tick,

        rx => tx_wire,

        data_out => data_out,
        data_valid => data_valid,
        framing_error => framing_error

    );

end Behavioral;

UART-VHDL/tb/uart_system_tb.vhd
library IEEE;
use IEEE.STD_LOGIC_1164.ALL;
use IEEE.NUMERIC_STD.ALL;

entity uart_system_tb is
end uart_system_tb;

architecture Behavioral of uart_system_tb is
    signal clk            : STD_LOGIC := '0';
    signal reset          : STD_LOGIC := '0';
    signal tick           : STD_LOGIC := '0';

    signal start          : STD_LOGIC := '0';
    signal data_in        : STD_LOGIC_VECTOR(7 downto 0) := (others => '0');

    signal data_out       : STD_LOGIC_VECTOR(7 downto 0);
    signal data_valid     : STD_LOGIC;

    signal busy           : STD_LOGIC;
    signal framing_error  : STD_LOGIC;

begin
    uut : entity work.uart_top
    port map(

        clk => clk,
        reset => reset,
        tick => tick,

        start => start,
        data_in => data_in,

        data_out => data_out,
        data_valid => data_valid,

        busy => busy,
        framing_error => framing_error

    );

    clock_process : process
    begin
        while true loop

            clk <= '0';
            wait for 10 ns;

            clk <= '1';
            wait for 10 ns;

        end loop;
    end process;

    tick_process : process
    begin
        while true loop

            tick <= '0';
            wait for 180 ns;

            tick <= '1';
            wait for 20 ns;

        end loop;
    end process;

    stimulus : process
    begin
        -- Reset
        reset <= '1';
        wait for 100 ns;

        reset <= '0';
        wait for 100 ns;

        -- Send A

        data_in <= "01000001";

        start <= '1';
        wait for 20 ns;
        start <= '0';

        wait until data_valid='1';

        assert data_out="01000001"
        report "A Failed"
        severity error;

        wait for 200 ns;

        -- Send 5

        data_in <= "00110101";

        start <= '1';
        wait for 20 ns;
        start <= '0';

        wait until data_valid='1';

        assert data_out="00110101"
        report "5 Failed"
        severity error;

        -- Verify no framing error
        assert framing_error='0'
        report "Unexpected Framing Error"
        severity error;

        report " ALL UART TESTS PASSED SUCCESSFULLY ";
        wait for 200 ns;

        assert false
        report "Simulation Finished"
        severity failure;
    end process;

    -- Monitor
    monitor : process(clk)
    begin
        if rising_edge(clk) then
            if data_valid='1' then
                report "Received Byte = "
                    & integer'image(
                        to_integer(unsigned(data_out))
                    );
            end if;
        end if;
    end process;
end Behavioral;

UART-VHDL/waveforms/uart_system.vcd
$date
  Mon Jun 22 08:10:00 2026
$end
$version
  GHDL v0
$end
$timescale
  1 fs
$end
$scope module standard $end
$upscope $end
$scope module std_logic_1164 $end
$upscope $end
$scope module numeric_std $end
$upscope $end
$scope module uart_system_tb $end
$var reg 1 ! clk $end
$var reg 1 " reset $end
$var reg 1 # tick $end
$var reg 1 $ start $end
$var reg 8 % data_in[7:0] $end
$var reg 8 & data_out[7:0] $end
$var reg 1 ' data_valid $end
$var reg 1 ( busy $end
$var reg 1 ) framing_error $end
$scope module uut $end
$var reg 1 * clk $end
$var reg 1 + reset $end
$var reg 1 , tick $end
$var reg 1 - start $end
$var reg 8 . data_in[7:0] $end
$var reg 8 / data_out[7:0] $end
$var reg 1 0 data_valid $end
$var reg 1 1 busy $end
$var reg 1 2 framing_error $end
$var reg 1 3 tx_wire $end
$scope module tx_inst $end
$var reg 1 4 clk $end
$var reg 1 5 reset $end
$var reg 1 6 tick $end
$var reg 1 7 start $end
$var reg 8 8 data_in[7:0] $end
$var reg 1 9 tx $end
$var reg 1 : busy $end
$comment current_state is not handled $end
$var reg 8 ; shift_reg[7:0] $end
$var integer 32 < bit_index $end
$upscope $end
$scope module rx_inst $end
$var reg 1 = clk $end
$var reg 1 > reset $end
$var reg 1 ? tick $end
$var reg 1 @ rx $end
$var reg 8 A data_out[7:0] $end
$var reg 1 B data_valid $end
$var reg 1 C framing_error $end
$comment current_state is not handled $end
$var reg 8 D shift_reg[7:0] $end
$var integer 32 E bit_index $end
$upscope $end
$upscope $end
$upscope $end
$enddefinitions $end
#0
0!
1"
0#
0$
b00000000 %
b00000000 &
0'
0(
0)
0*
1+
0,
0-
b00000000 .
b00000000 /
00
01
02
13
04
15
06
07
b00000000 8
19
0:
b00000000 ;
b0 <
0=
1>
0?
1@
b00000000 A
0B
0C
b00000000 D
b0 E
#10000000
1!
1*
14
1=
#20000000
0!
0*
04
0=
#30000000
1!
1*
14
1=
#40000000
0!
0*
04
0=
#50000000
1!
1*
14
1=
#60000000
0!
0*
04
0=
#70000000
1!
1*
14
1=
#80000000
0!
0*
04
0=
#90000000
1!
1*
14
1=
#100000000
0!
0"
0*
0+
04
05
0=
0>
#110000000
1!
1*
14
1=
#120000000
0!
0*
04
0=
#130000000
1!
1*
14
1=
#140000000
0!
0*
04
0=
#150000000
1!
1*
14
1=
#160000000
0!
0*
04
0=
#170000000
1!
1*
14
1=
#180000000
0!
1#
0*
1,
04
16
0=
1?
#190000000
1!
1*
14
1=
#200000000
0!
0#
1$
b01000001 %
0*
0,
1-
b01000001 .
04
06
17
b01000001 8
0=
0?
#210000000
1!
1(
1*
11
14
1:
b01000001 ;
1=
#220000000
0!
0$
0*
0-
04
07
0=
#230000000
1!
1*
03
14
09
1=
0@
#240000000
0!
0*
04
0=
#250000000
1!
1*
14
1=
#260000000
0!
0*
04
0=
#270000000
1!
1*
14
1=
#280000000
0!
0*
04
0=
#290000000
1!
1*
14
1=
#300000000
0!
0*
04
0=
#310000000
1!
1*
14
1=
#320000000
0!
0*
04
0=
#330000000
1!
1*
14
1=
#340000000
0!
0*
04
0=
#350000000
1!
1*
14
1=
#360000000
0!
0*
04
0=
#370000000
1!
1*
14
1=
#380000000
0!
1#
0*
1,
04
16
0=
1?
#390000000
1!
1*
14
1=
#400000000
0!
0#
0*
0,
04
06
0=
0?
#410000000
1!
1*
13
14
19
1=
1@
#420000000
0!
0*
04
0=
#430000000
1!
1*
14
1=
#440000000
0!
0*
04
0=
#450000000
1!
1*
14
1=
#460000000
0!
0*
04
0=
#470000000
1!
1*
14
1=
#480000000
0!
0*
04
0=
#490000000
1!
1*
14
1=
#500000000
0!
0*
04
0=
#510000000
1!
1*
14
1=
#520000000
0!
0*
04
0=
#530000000
1!
1*
14
1=
#540000000
0!
0*
04
0=
#550000000
1!
1*
14
1=
#560000000
0!
0*
04
0=
#570000000
1!
1*
14
1=
#580000000
0!
1#
0*
1,
04
16
0=
1?
#590000000
1!
1*
14
b1 <
1=
b00000001 D
b1 E
#600000000
0!
0#
0*
0,
04
06
0=
0?
#610000000
1!
1*
03
14
09
1=
0@
#620000000
0!
0*
04
0=
#630000000
1!
1*
14
1=
#640000000
0!
0*
04
0=
#650000000
1!
1*
14
1=
#660000000
0!
0*
04
0=
#670000000
1!
1*
14
1=
#680000000
0!
0*
04
0=
#690000000
1!
1*
14
1=
#700000000
0!
0*
04
0=
#710000000
1!
1*
14
1=
#720000000
0!
0*
04
0=
#730000000
1!
1*
14
1=
#740000000
0!
0*
04
0=
#750000000
1!
1*
14
1=
#760000000
0!
0*
04
0=
#770000000
1!
1*
14
1=
#780000000
0!
1#
0*
1,
04
16
0=
1?
#790000000
1!
1*
14
b10 <
1=
b10 E
#800000000
0!
0#
0*
0,
04
06
0=
0?
#810000000
1!
1*
14
1=
#820000000
0!
0*
04
0=
#830000000
1!
1*
14
1=
#840000000
0!
0*
04
0=
#850000000
1!
1*
14
1=
#860000000
0!
0*
04
0=
#870000000
1!
1*
14
1=
#880000000
0!
0*
04
0=
#890000000
1!
1*
14
1=
#900000000
0!
0*
04
0=
#910000000
1!
1*
14
1=
#920000000
0!
0*
04
0=
#930000000
1!
1*
14
1=
#940000000
0!
0*
04
0=
#950000000
1!
1*
14
1=
#960000000
0!
0*
04
0=
#970000000
1!
1*
14
1=
#980000000
0!
1#
0*
1,
04
16
0=
1?
#990000000
1!
1*
14
b11 <
1=
b11 E
#1000000000
0!
0#
0*
0,
04
06
0=
0?
#1010000000
1!
1*
14
1=
#1020000000
0!
0*
04
0=
#1030000000
1!
1*
14
1=
#1040000000
0!
0*
04
0=
#1050000000
1!
1*
14
1=
#1060000000
0!
0*
04
0=
#1070000000
1!
1*
14
1=
#1080000000
0!
0*
04
0=
#1090000000
1!
1*
14
1=
#1100000000
0!
0*
04
0=
#1110000000
1!
1*
14
1=
#1120000000
0!
0*
04
0=
#1130000000
1!
1*
14
1=
#1140000000
0!
0*
04
0=
#1150000000
1!
1*
14
1=
#1160000000
0!
0*
04
0=
#1170000000
1!
1*
14
1=
#1180000000
0!
1#
0*
1,
04
16
0=
1?
#1190000000
1!
1*
14
b100 <
1=
b100 E
#1200000000
0!
0#
0*
0,
04
06
0=
0?
#1210000000
1!
1*
14
1=
#1220000000
0!
0*
04
0=
#1230000000
1!
1*
14
1=
#1240000000
0!
0*
04
0=
#1250000000
1!
1*
14
1=
#1260000000
0!
0*
04
0=
#1270000000
1!
1*
14
1=
#1280000000
0!
0*
04
0=
#1290000000
1!
1*
14
1=
#1300000000
0!
0*
04
0=
#1310000000
1!
1*
14
1=
#1320000000
0!
0*
04
0=
#1330000000
1!
1*
14
1=
#1340000000
0!
0*
04
0=
#1350000000
1!
1*
14
1=
#1360000000
0!
0*
04
0=
#1370000000
1!
1*
14
1=
#1380000000
0!
1#
0*
1,
04
16
0=
1?
#1390000000
1!
1*
14
b101 <
1=
b101 E
#1400000000
0!
0#
0*
0,
04
06
0=
0?
#1410000000
1!
1*
14
1=
#1420000000
0!
0*
04
0=
#1430000000
1!
1*
14
1=
#1440000000
0!
0*
04
0=
#1450000000
1!
1*
14
1=
#1460000000
0!
0*
04
0=
#1470000000
1!
1*
14
1=
#1480000000
0!
0*
04
0=
#1490000000
1!
1*
14
1=
#1500000000
0!
0*
04
0=
#1510000000
1!
1*
14
1=
#1520000000
0!
0*
04
0=
#1530000000
1!
1*
14
1=
#1540000000
0!
0*
04
0=
#1550000000
1!
1*
14
1=
#1560000000
0!
0*
04
0=
#1570000000
1!
1*
14
1=
#1580000000
0!
1#
0*
1,
04
16
0=
1?
#1590000000
1!
1*
14
b110 <
1=
b110 E
#1600000000
0!
0#
0*
0,
04
06
0=
0?
#1610000000
1!
1*
13
14
19
1=
1@
#1620000000
0!
0*
04
0=
#1630000000
1!
1*
14
1=
#1640000000
0!
0*
04
0=
#1650000000
1!
1*
14
1=
#1660000000
0!
0*
04
0=
#1670000000
1!
1*
14
1=
#1680000000
0!
0*
04
0=
#1690000000
1!
1*
14
1=
#1700000000
0!
0*
04
0=
#1710000000
1!
1*
14
1=
#1720000000
0!
0*
04
0=
#1730000000
1!
1*
14
1=
#1740000000
0!
0*
04
0=
#1750000000
1!
1*
14
1=
#1760000000
0!
0*
04
0=
#1770000000
1!
1*
14
1=
#1780000000
0!
1#
0*
1,
04
16
0=
1?
#1790000000
1!
1*
14
b111 <
1=
b01000001 D
b111 E
#1800000000
0!
0#
0*
0,
04
06
0=
0?
#1810000000
1!
1*
03
14
09
1=
0@
#1820000000
0!
0*
04
0=
#1830000000
1!
1*
14
1=
#1840000000
0!
0*
04
0=
#1850000000
1!
1*
14
1=
#1860000000
0!
0*
04
0=
#1870000000
1!
1*
14
1=
#1880000000
0!
0*
04
0=
#1890000000
1!
1*
14
1=
#1900000000
0!
0*
04
0=
#1910000000
1!
1*
14
1=
#1920000000
0!
0*
04
0=
#1930000000
1!
1*
14
1=
#1940000000
0!
0*
04
0=
#1950000000
1!
1*
14
1=
#1960000000
0!
0*
04
0=
#1970000000
1!
1*
14
1=
#1980000000
0!
1#
0*
1,
04
16
0=
1?
#1990000000
1!
1*
14
b0 <
1=
#2000000000
0!
0#
0*
0,
04
06
0=
0?
#2010000000
1!
1*
13
14
19
1=
1@
#2020000000
0!
0*
04
0=
#2030000000
1!
1*
14
1=
#2040000000
0!
0*
04
0=
#2050000000
1!
1*
14
1=
#2060000000
0!
0*
04
0=
#2070000000
1!
1*
14
1=
#2080000000
0!
0*
04
0=
#2090000000
1!
1*
14
1=
#2100000000
0!
0*
04
0=
#2110000000
1!
1*
14
1=
#2120000000
0!
0*
04
0=
#2130000000
1!
1*
14
1=
#2140000000
0!
0*
04
0=
#2150000000
1!
1*
14
1=
#2160000000
0!
0*
04
0=
#2170000000
1!
1*
14
1=
#2180000000
0!
1#
0*
1,
04
16
0=
1?
#2190000000
1!
b01000001 &
1'
1*
b01000001 /
10
14
1=
b01000001 A
1B
#2200000000
0!
0#
0*
0,
04
06
0=
0?
#2210000000
1!
0'
0(
1*
00
01
14
0:
1=
0B
#2220000000
0!
0*
04
0=
#2230000000
1!
1*
14
1=
#2240000000
0!
0*
04
0=
#2250000000
1!
1*
14
1=
#2260000000
0!
0*
04
0=
#2270000000
1!
1*
14
1=
#2280000000
0!
0*
04
0=
#2290000000
1!
1*
14
1=
#2300000000
0!
0*
04
0=
#2310000000
1!
1*
14
1=
#2320000000
0!
0*
04
0=
#2330000000
1!
1*
14
1=
#2340000000
0!
0*
04
0=
#2350000000
1!
1*
14
1=
#2360000000
0!
0*
04
0=
#2370000000
1!
1*
14
1=
#2380000000
0!
1#
0*
1,
04
16
0=
1?
#2390000000
1!
1$
b00110101 %
1(
1*
1-
b00110101 .
11
14
17
b00110101 8
1:
b00110101 ;
1=
#2400000000
0!
0#
0*
0,
04
06
0=
0?
#2410000000
1!
0$
1*
0-
03
14
07
09
1=
0@
#2420000000
0!
0*
04
0=
#2430000000
1!
1*
14
1=
b0 E
#2440000000
0!
0*
04
0=
#2450000000
1!
1*
14
1=
#2460000000
0!
0*
04
0=
#2470000000
1!
1*
14
1=
#2480000000
0!
0*
04
0=
#2490000000
1!
1*
14
1=
#2500000000
0!
0*
04
0=
#2510000000
1!
1*
14
1=
#2520000000
0!
0*
04
0=
#2530000000
1!
1*
14
1=
#2540000000
0!
0*
04
0=
#2550000000
1!
1*
14
1=
#2560000000
0!
0*
04
0=
#2570000000
1!
1*
14
1=
#2580000000
0!
1#
0*
1,
04
16
0=
1?
#2590000000
1!
1*
14
1=
#2600000000
0!
0#
0*
0,
04
06
0=
0?
#2610000000
1!
1*
13
14
19
1=
1@
#2620000000
0!
0*
04
0=
#2630000000
1!
1*
14
1=
#2640000000
0!
0*
04
0=
#2650000000
1!
1*
14
1=
#2660000000
0!
0*
04
0=
#2670000000
1!
1*
14
1=
#2680000000
0!
0*
04
0=
#2690000000
1!
1*
14
1=
#2700000000
0!
0*
04
0=
#2710000000
1!
1*
14
1=
#2720000000
0!
0*
04
0=
#2730000000
1!
1*
14
1=
#2740000000
0!
0*
04
0=
#2750000000
1!
1*
14
1=
#2760000000
0!
0*
04
0=
#2770000000
1!
1*
14
1=
#2780000000
0!
1#
0*
1,
04
16
0=
1?
#2790000000
1!
1*
14
b1 <
1=
b1 E
#2800000000
0!
0#
0*
0,
04
06
0=
0?
#2810000000
1!
1*
03
14
09
1=
0@
#2820000000
0!
0*
04
0=
#2830000000
1!
1*
14
1=
#2840000000
0!
0*
04
0=
#2850000000
1!
1*
14
1=
#2860000000
0!
0*
04
0=
#2870000000
1!
1*
14
1=
#2880000000
0!
0*
04
0=
#2890000000
1!
1*
14
1=
#2900000000
0!
0*
04
0=
#2910000000
1!
1*
14
1=
#2920000000
0!
0*
04
0=
#2930000000
1!
1*
14
1=
#2940000000
0!
0*
04
0=
#2950000000
1!
1*
14
1=
#2960000000
0!
0*
04
0=
#2970000000
1!
1*
14
1=
#2980000000
0!
1#
0*
1,
04
16
0=
1?
#2990000000
1!
1*
14
b10 <
1=
b10 E
#3000000000
0!
0#
0*
0,
04
06
0=
0?
#3010000000
1!
1*
13
14
19
1=
1@
#3020000000
0!
0*
04
0=
#3030000000
1!
1*
14
1=
#3040000000
0!
0*
04
0=
#3050000000
1!
1*
14
1=
#3060000000
0!
0*
04
0=
#3070000000
1!
1*
14
1=
#3080000000
0!
0*
04
0=
#3090000000
1!
1*
14
1=
#3100000000
0!
0*
04
0=
#3110000000
1!
1*
14
1=
#3120000000
0!
0*
04
0=
#3130000000
1!
1*
14
1=
#3140000000
0!
0*
04
0=
#3150000000
1!
1*
14
1=
#3160000000
0!
0*
04
0=
#3170000000
1!
1*
14
1=
#3180000000
0!
1#
0*
1,
04
16
0=
1?
#3190000000
1!
1*
14
b11 <
1=
b01000101 D
b11 E
#3200000000
0!
0#
0*
0,
04
06
0=
0?
#3210000000
1!
1*
03
14
09
1=
0@
#3220000000
0!
0*
04
0=
#3230000000
1!
1*
14
1=
#3240000000
0!
0*
04
0=
#3250000000
1!
1*
14
1=
#3260000000
0!
0*
04
0=
#3270000000
1!
1*
14
1=
#3280000000
0!
0*
04
0=
#3290000000
1!
1*
14
1=
#3300000000
0!
0*
04
0=
#3310000000
1!
1*
14
1=
#3320000000
0!
0*
04
0=
#3330000000
1!
1*
14
1=
#3340000000
0!
0*
04
0=
#3350000000
1!
1*
14
1=
#3360000000
0!
0*
04
0=
#3370000000
1!
1*
14
1=
#3380000000
0!
1#
0*
1,
04
16
0=
1?
#3390000000
1!
1*
14
b100 <
1=
b100 E
#3400000000
0!
0#
0*
0,
04
06
0=
0?
#3410000000
1!
1*
13
14
19
1=
1@
#3420000000
0!
0*
04
0=
#3430000000
1!
1*
14
1=
#3440000000
0!
0*
04
0=
#3450000000
1!
1*
14
1=
#3460000000
0!
0*
04
0=
#3470000000
1!
1*
14
1=
#3480000000
0!
0*
04
0=
#3490000000
1!
1*
14
1=
#3500000000
0!
0*
04
0=
#3510000000
1!
1*
14
1=
#3520000000
0!
0*
04
0=
#3530000000
1!
1*
14
1=
#3540000000
0!
0*
04
0=
#3550000000
1!
1*
14
1=
#3560000000
0!
0*
04
0=
#3570000000
1!
1*
14
1=
#3580000000
0!
1#
0*
1,
04
16
0=
1?
#3590000000
1!
1*
14
b101 <
1=
b01010101 D
b101 E
#3600000000
0!
0#
0*
0,
04
06
0=
0?
#3610000000
1!
1*
14
1=
#3620000000
0!
0*
04
0=
#3630000000
1!
1*
14
1=
#3640000000
0!
0*
04
0=
#3650000000
1!
1*
14
1=
#3660000000
0!
0*
04
0=
#3670000000
1!
1*
14
1=
#3680000000
0!
0*
04
0=
#3690000000
1!
1*
14
1=
#3700000000
0!
0*
04
0=
#3710000000
1!
1*
14
1=
#3720000000
0!
0*
04
0=
#3730000000
1!
1*
14
1=
#3740000000
0!
0*
04
0=
#3750000000
1!
1*
14
1=
#3760000000
0!
0*
04
0=
#3770000000
1!
1*
14
1=
#3780000000
0!
1#
0*
1,
04
16
0=
1?
#3790000000
1!
1*
14
b110 <
1=
b01110101 D
b110 E
#3800000000
0!
0#
0*
0,
04
06
0=
0?
#3810000000
1!
1*
03
14
09
1=
0@
#3820000000
0!
0*
04
0=
#3830000000
1!
1*
14
1=
#3840000000
0!
0*
04
0=
#3850000000
1!
1*
14
1=
#3860000000
0!
0*
04
0=
#3870000000
1!
1*
14
1=
#3880000000
0!
0*
04
0=
#3890000000
1!
1*
14
1=
#3900000000
0!
0*
04
0=
#3910000000
1!
1*
14
1=
#3920000000
0!
0*
04
0=
#3930000000
1!
1*
14
1=
#3940000000
0!
0*
04
0=
#3950000000
1!
1*
14
1=
#3960000000
0!
0*
04
0=
#3970000000
1!
1*
14
1=
#3980000000
0!
1#
0*
1,
04
16
0=
1?
#3990000000
1!
1*
14
b111 <
1=
b00110101 D
b111 E
#4000000000
0!
0#
0*
0,
04
06
0=
0?
#4010000000
1!
1*
14
1=
#4020000000
0!
0*
04
0=
#4030000000
1!
1*
14
1=
#4040000000
0!
0*
04
0=
#4050000000
1!
1*
14
1=
#4060000000
0!
0*
04
0=
#4070000000
1!
1*
14
1=
#4080000000
0!
0*
04
0=
#4090000000
1!
1*
14
1=
#4100000000
0!
0*
04
0=
#4110000000
1!
1*
14
1=
#4120000000
0!
0*
04
0=
#4130000000
1!
1*
14
1=
#4140000000
0!
0*
04
0=
#4150000000
1!
1*
14
1=
#4160000000
0!
0*
04
0=
#4170000000
1!
1*
14
1=
#4180000000
0!
1#
0*
1,
04
16
0=
1?
#4190000000
1!
1*
14
b0 <
1=
#4200000000
0!
0#
0*
0,
04
06
0=
0?
#4210000000
1!
1*
13
14
19
1=
1@
#4220000000
0!
0*
04
0=
#4230000000
1!
1*
14
1=
#4240000000
0!
0*
04
0=
#4250000000
1!
1*
14
1=
#4260000000
0!
0*
04
0=
#4270000000
1!
1*
14
1=
#4280000000
0!
0*
04
0=
#4290000000
1!
1*
14
1=
#4300000000
0!
0*
04
0=
#4310000000
1!
1*
14
1=
#4320000000
0!
0*
04
0=
#4330000000
1!
1*
14
1=
#4340000000
0!
0*
04
0=
#4350000000
1!
1*
14
1=
#4360000000
0!
0*
04
0=
#4370000000
1!
1*
14
1=
#4380000000
0!
1#
0*
1,
04
16
0=
1?
#4390000000
1!
b00110101 &
1'
1*
b00110101 /
10
14
1=
b00110101 A
1B
#4400000000
0!
0#
0*
0,
04
06
0=
0?
#4410000000
1!
0'
0(
1*
00
01
14
0:
1=
0B
#4420000000
0!
0*
04
0=
#4430000000
1!
1*
14
1=
#4440000000
0!
0*
04
0=
#4450000000
1!
1*
14
1=
#4460000000
0!
0*
04
0=
#4470000000
1!
1*
14
1=
#4480000000
0!
0*
04
0=
#4490000000
1!
1*
14
1=
#4500000000
0!
0*
04
0=
#4510000000
1!
1*
14
1=
#4520000000
0!
0*
04
0=
#4530000000
1!
1*
14
1=
#4540000000
0!
0*
04
0=
#4550000000
1!
1*
14
1=
#4560000000
0!
0*
04
0=
#4570000000
1!
1*
14
1=
#4580000000
0!
1#
0*
1,
04
16
0=
1?
